datadagger/__init__.py
datadagger/cli.py
datadagger/analyzers/__init__.py
datadagger/analyzers/narrative_tracker.py
datadagger/analyzers/text_analyzer.py
datadagger/commands/__init__.py
datadagger/commands/config.py
datadagger/commands/correlate.py
datadagger/commands/demo.py
datadagger/commands/export.py
datadagger/commands/network.py
datadagger/commands/origin.py
datadagger/commands/pricing.py
datadagger/commands/search.py
datadagger/commands/sentiment.py
datadagger/commands/setup.py
datadagger/commands/timeline.py
datadagger/commands/track.py
datadagger/scrapers/__init__.py
datadagger/scrapers/mastodon_scraper.py
datadagger/scrapers/reddit_scraper.py
datadagger/scrapers/twitter_scraper.py
datadagger/utils/__init__.py
datadagger/utils/config.py
datadagger/utils/data_store.py
datadagger/visualizers/__init__.py
datadagger/visualizers/timeline_viz.py
datadagger-2.0.0.dist-info/licenses/LICENSE
datadagger-2.0.0.dist-info/METADATA
datadagger-2.0.0.dist-info/WHEEL
datadagger-2.0.0.dist-info/entry_points.txt
datadagger-2.0.0.dist-info/top_level.txt
datadagger-2.0.0.dist-info/RECORD
