Metadata-Version: 2.4
Name: datadagger
Version: 2.0.0
Summary: Influence Archaeology OSINT Tool for mapping information flow across digital communities
Author: Security Research Team
Project-URL: Homepage, https://github.com/yourusername/datadagger
Project-URL: Bug Reports, https://github.com/yourusername/datadagger/issues
Project-URL: Source, https://github.com/yourusername/datadagger
Keywords: osint,social media,narrative tracking,misinformation,security research
Classifier: Development Status :: 4 - Beta
Classifier: Intended Audience :: Information Technology
Classifier: Operating System :: OS Independent
Classifier: Programming Language :: Python :: 3
Classifier: Programming Language :: Python :: 3.8
Classifier: Programming Language :: Python :: 3.9
Classifier: Programming Language :: Python :: 3.10
Classifier: Programming Language :: Python :: 3.11
Classifier: Topic :: Security
Classifier: Topic :: Internet :: WWW/HTTP :: Indexing/Search
Classifier: Topic :: Scientific/Engineering :: Information Analysis
Requires-Python: >=3.8
License-File: LICENSE
Requires-Dist: click
Requires-Dist: requests
Requires-Dist: beautifulsoup4
Requires-Dist: pandas<2.1.0
Requires-Dist: numpy<1.25.0
Requires-Dist: matplotlib
Requires-Dist: seaborn
Requires-Dist: networkx
Requires-Dist: nltk
Requires-Dist: spacy<3.7.0
Requires-Dist: textblob
Requires-Dist: plotly
Requires-Dist: python-dateutil
Requires-Dist: praw
Requires-Dist: tweepy
Requires-Dist: aiohttp
Requires-Dist: python-dotenv
Requires-Dist: rich
Requires-Dist: typer
Requires-Dist: Mastodon.py
Requires-Dist: scikit-learn<1.3.0
Requires-Dist: textdistance
Requires-Dist: wordcloud
Dynamic: license-file
Dynamic: requires-python
